blinka_displayio_pygamedisplay.py
blinka_displayio_pygamedisplay-4.0.0.dist-info/licenses/LICENSE
blinka_displayio_pygamedisplay-4.0.0.dist-info/METADATA
blinka_displayio_pygamedisplay-4.0.0.dist-info/WHEEL
blinka_displayio_pygamedisplay-4.0.0.dist-info/top_level.txt
blinka_displayio_pygamedisplay-4.0.0.dist-info/RECORD
