Metadata-Version: 2.4
Name: blinka-displayio-pygamedisplay
Version: 4.0.0
Summary: Use CircuitPython displayio code on PC and Raspberry Pi outputting to a PyGame window instead of a physical display.
Author-email: Tim C <foamyguy@gmail.com>
License: MIT
Project-URL: Homepage, https://github.com/foamyguy/Blinka_Displayio_PyGameDisplay
Keywords: adafruit,blinka,circuitpython,micropython,blinka_displayio_pygamedisplay,displayio,hdmi,pc,window,pygame
Classifier: Development Status :: 3 - Alpha
Classifier: Intended Audience :: Developers
Classifier: Topic :: Software Development :: Libraries
Classifier: Topic :: System :: Hardware
Classifier: License :: OSI Approved :: MIT License
Classifier: Programming Language :: Python :: 3
Classifier: Programming Language :: Python :: 3.4
Classifier: Programming Language :: Python :: 3.5
License-File: LICENSE
Requires-Dist: adafruit-blinka-displayio
Requires-Dist: pygame>=2.1.3dev8
Requires-Dist: numpy
Provides-Extra: optional
Dynamic: license-file
